submix/__init__.py
submix/__main__.py
submix/asgi.py
submix/cli.py
submix/parser.py
submix/server.py
submix/settings.py
submix/urls.py
submix/views.py
submix/wsgi.py
submix/gen/__init__.py
submix/gen/clash.py
submix-0.0.1.dist-info/LICENSE
submix-0.0.1.dist-info/METADATA
submix-0.0.1.dist-info/WHEEL
submix-0.0.1.dist-info/top_level.txt
submix-0.0.1.dist-info/RECORD
