Metadata-Version: 2.1
Name: submix
Version: 0.0.1
Summary: UNKNOWN
Home-page: UNKNOWN
Author: UNKNOWN
Author-email: UNKNOWN
License: UNKNOWN
Platform: UNKNOWN
Requires-Dist: Django (>=3.0.3)
Requires-Dist: requests (>=2.22.0)
